fastddm/__init__.py
fastddm/_config.py
fastddm/_core.cp311-win_amd64.pyd
fastddm/_ddm.py
fastddm/_ddm_cpp.py
fastddm/_ddm_python.py
fastddm/_fftopt.py
fastddm/_io.py
fastddm/_io_common.py
fastddm/azimuthalaverage.py
fastddm/fddm.dll
fastddm/fftw3.dll
fastddm/fit.py
fastddm/fit_models.py
fastddm/imagestructurefunction.py
fastddm/intermediatescatteringfunction.py
fastddm/lags.py
fastddm/mask.py
fastddm/noise_est.py
fastddm/setup.py
fastddm/utils.py
fastddm/weights.py
fastddm/window.py
fastddm-0.3.14.dist-info/licenses/LICENSE
fastddm-0.3.14.dist-info/METADATA
fastddm-0.3.14.dist-info/WHEEL
fastddm-0.3.14.dist-info/top_level.txt
fastddm-0.3.14.dist-info/RECORD
