Metadata-Version: 2.4
Name: fastddm
Version: 0.3.14
Summary: A Python/C++ library for the analysis of Differential Dynamic Microscopy experiments
Home-page: https://github.com/somexlab/fastddm
Author: Enrico Lattuada, Fabian Krautgasser, Maxime Lavaudd, Roberto Cerbino
Author-email: cerbino@gmail.com
Maintainer-email: Enrico Lattuada <lattuada.enrico@gmail.com>, Maxime Lavaud <lavaudmaxime.ml@gmail.com>
License: GNU GPL 3.0
Project-URL: Source, https://github.com/somexlab/fastddm
Project-URL: Documentation, https://fastddm.readthedocs.io
Project-URL: Issues, https://github.com/somexlab/fastddm/issues
Project-URL: Changelog, https://github.com/somexlab/fastddm/blob/main/CHANGELOG.rst
Keywords: cuda,differential-dynamic-microscopy,digital-fourier-microscopy,gpu,image-analysis,microscopy,python
Classifier: Development Status :: 4 - Beta
Classifier: Environment :: Console
Classifier: Intended Audience :: Science/Research
Classifier: License :: OSI Approved :: GNU General Public License v3 (GPLv3)
Classifier: Operating System :: OS Independent
Classifier: Programming Language :: Python :: 3
Classifier: Programming Language :: C++
Classifier: Topic :: Scientific/Engineering :: Image Processing
Classifier: Topic :: Scientific/Engineering :: Physics
Requires-Python: >=3.9
License-File: LICENSE
Requires-Dist: psutil
Requires-Dist: numpy
Requires-Dist: scipy
Requires-Dist: matplotlib
Requires-Dist: scikit-image
Requires-Dist: tifffile
Requires-Dist: nd2reader
Requires-Dist: pandas
Requires-Dist: lmfit
Provides-Extra: test
Requires-Dist: pytest; extra == "test"
Requires-Dist: pytest-regtest; extra == "test"
Provides-Extra: doc
Requires-Dist: sphinx; extra == "doc"
Requires-Dist: sphinx-tabs; extra == "doc"
Requires-Dist: nbsphinx; extra == "doc"
Requires-Dist: furo; extra == "doc"
Requires-Dist: ipython; extra == "doc"
Provides-Extra: dev
Requires-Dist: fastddm[doc,test]; extra == "dev"
Dynamic: home-page
Dynamic: license
Dynamic: license-file
